receive/__init__.py
receive/server.py
receive-0.1.1.dist-info/WHEEL
receive-0.1.1.dist-info/METADATA
receive-0.1.1.dist-info/RECORD
