Metadata-Version: 2.1
Name: receive
Version: 0.1.1
Summary: Host a temporary HTTP server to receive a web-hook callback.
License: GPL
Author: Blake Smith
Author-email: blakeinvictoria@gmail.com
Requires-Python: >=3.8,<4.0
Classifier: License :: Other/Proprietary License
Classifier: Programming Language :: Python :: 3
Classifier: Programming Language :: Python :: 3.8
Classifier: Programming Language :: Python :: 3.9
Requires-Dist: aiohttp (>=3.7.4,<4.0.0)
